ttlru_map/__init__.py
ttlru_map/_exceptions.py
ttlru_map/_linked_list.py
ttlru_map/_ttl_map.py
ttlru_map/py.typed
ttlru_map-1.1.0.dist-info/METADATA
ttlru_map-1.1.0.dist-info/WHEEL
ttlru_map-1.1.0.dist-info/licenses/LICENSE
ttlru_map-1.1.0.dist-info/RECORD
