Metadata-Version: 2.3
Name: ttlru-map
Version: 1.1.0
Summary: Custom Mapping with TTL and LRU support.
Project-URL: Changelog, https://github.com/zoola969/python_ttlru_map/CHANGELOG.md
Project-URL: Documentation, https://python_ttlru_map.readthedocs.io/en/latest/
Project-URL: Homepage, https://github.com/zoola969/python_ttlru_map
Project-URL: Issues, https://github.com/zoola969/python_ttlru_map/issues
Project-URL: Repository, https://github.com/zoola969/python_ttlru_map.git
Author-email: Alexander Dmitriev <zoola969@gmail.com>
License:                                  Apache License
Keywords: cache,dict,expire,expired,lru,lru-cache,mapping,time-to-live,ttl
Classifier: Development Status :: 5 - Production/Stable
Classifier: Intended Audience :: Developers
Classifier: License :: OSI Approved :: Apache Software License
Classifier: Operating System :: OS Independent
Classifier: Programming Language :: Python
Classifier: Programming Language :: Python :: 3
Classifier: Programming Language :: Python :: 3.9
Classifier: Programming Language :: Python :: 3.10
Classifier: Programming Language :: Python :: 3.11
Classifier: Programming Language :: Python :: 3.12
Classifier: Programming Language :: Python :: 3.13
Classifier: Topic :: Software Development :: Libraries
Classifier: Typing :: Typed
Requires-Python: >=3.9
Provides-Extra: benchmarks
Requires-Dist: perfplot~=0.10; extra == 'benchmarks'
Provides-Extra: build
Requires-Dist: hatch~=1.7; extra == 'build'
Provides-Extra: docs
Requires-Dist: sphinx<9.0,>=7.2; extra == 'docs'
Provides-Extra: test
Requires-Dist: coverage~=7.3; extra == 'test'
Requires-Dist: mypy~=1.13; extra == 'test'
Requires-Dist: pytest~=8.1; extra == 'test'
